dk_api_client/__init__.py
dk_api_client/api_client.py
dk_api_client/configuration.py
dk_api_client/rest.py
dk_api_client/api/__init__.py
dk_api_client/api/product_search_api.py
dk_api_client/models/__init__.py
dk_api_client/models/base_filter_v3.py
dk_api_client/models/base_product.py
dk_api_client/models/break_price.py
dk_api_client/models/categories_response.py
dk_api_client/models/category.py
dk_api_client/models/category_node.py
dk_api_client/models/category_response.py
dk_api_client/models/classifications.py
dk_api_client/models/description.py
dk_api_client/models/digi_reel_pricing.py
dk_api_client/models/dk_problem_details.py
dk_api_client/models/filter_id.py
dk_api_client/models/filter_options.py
dk_api_client/models/filter_options_request.py
dk_api_client/models/filter_value.py
dk_api_client/models/iso_search_locale.py
dk_api_client/models/keyword_request.py
dk_api_client/models/keyword_response.py
dk_api_client/models/manufacturer.py
dk_api_client/models/manufacturer_info.py
dk_api_client/models/manufacturers_response.py
dk_api_client/models/media_links.py
dk_api_client/models/media_response.py
dk_api_client/models/package_type.py
dk_api_client/models/package_type_by_quantity_product.py
dk_api_client/models/package_type_by_quantity_response.py
dk_api_client/models/parameter.py
dk_api_client/models/parameter_filter_options_response.py
dk_api_client/models/parameter_filter_request.py
dk_api_client/models/parameter_value.py
dk_api_client/models/parametric_category.py
dk_api_client/models/price_break.py
dk_api_client/models/product.py
dk_api_client/models/product_associations.py
dk_api_client/models/product_associations_response.py
dk_api_client/models/product_details.py
dk_api_client/models/product_status_v3.py
dk_api_client/models/product_substitute.py
dk_api_client/models/product_substitutes_response.py
dk_api_client/models/product_summary.py
dk_api_client/models/product_variation.py
dk_api_client/models/recommendation.py
digikey_apiv4-1.0.0.dist-info/METADATA
digikey_apiv4-1.0.0.dist-info/WHEEL
digikey_apiv4-1.0.0.dist-info/top_level.txt
digikey_apiv4-1.0.0.dist-info/RECORD
